dj_sessions-0.4.0.dist-info/DESCRIPTION.rst
dj_sessions-0.4.0.dist-info/METADATA
dj_sessions-0.4.0.dist-info/RECORD
dj_sessions-0.4.0.dist-info/WHEEL
dj_sessions-0.4.0.dist-info/metadata.json
dj_sessions-0.4.0.dist-info/top_level.txt
djsessions/__init__.py
djsessions/admin.py
djsessions/apps.py
djsessions/models.py
djsessions/signals.py
djsessions/utils.py
djsessions/management/__init__.py
djsessions/management/commands/__init__.py
djsessions/management/commands/clear_channel_sessions.py
djsessions/migrations/0001_initial.py
djsessions/migrations/__init__.py
djsessions/static/css/djsessions.css
djsessions/static/js/djsessions.js
djsessions/templates/djsessions/base.html
