Metadata-Version: 2.0
Name: dj-sessions
Version: 0.4.0
Summary: Enhanced session traciking for Django
Home-page: https://gitlab.com/pydanny/dj-sessions
Author: Daniel and Audrey Roy Greenfeld
Author-email: pydanny@gmail.com
License: Apache Software License 2.0
Keywords: dj-sessions
Platform: UNKNOWN
Classifier: Development Status :: 3 - Alpha
Classifier: Framework :: Django
Classifier: Framework :: Django :: 1.8
Classifier: Framework :: Django :: 1.9
Classifier: Intended Audience :: Developers
Classifier: License :: OSI Approved :: BSD License
Classifier: Natural Language :: English
Classifier: Programming Language :: Python :: 2
Classifier: Programming Language :: Python :: 2.7
Classifier: Programming Language :: Python :: 3
Classifier: Programming Language :: Python :: 3.2
Classifier: Programming Language :: Python :: 3.3
Classifier: Programming Language :: Python :: 3.4
Classifier: Programming Language :: Python :: 3.5
Requires-Dist: django-model-utils (>=2.0)
